mysql_connector_py/__init__.py
mysql_connector_py-999.0.5.dist-info/licenses/LICENSE.txt
mysql_connector_py-999.0.5.dist-info/METADATA
mysql_connector_py-999.0.5.dist-info/WHEEL
mysql_connector_py-999.0.5.dist-info/top_level.txt
mysql_connector_py-999.0.5.dist-info/RECORD
