Metadata-Version: 2.4
Name: mysql-connector-py
Version: 999.0.5
Summary: A self-contained Python driver for communicating with MySQL servers, using an API that is compliant with the Python Database API Specification v2.0 (PEP 249).
Home-page: https://github.com/oracle/mysql-connector-py
Author: OracleForks
Author-email: your.email@example.com
License: GNU GPLv2 (with FOSS License Exception)
Project-URL: Homepage, https://dev.mysql.com/doc/connector-python/en/
Project-URL: Documentation, https://dev.mysql.com/doc/connector-python/en/
Project-URL: Downloads, https://dev.mysql.com/downloads/connector/python/
Project-URL: Release Notes, https://dev.mysql.com/doc/relnotes/connector-python/en/
Project-URL: Bug System, https://bugs.mysql.com/
Project-URL: Slack, https://mysqlcommunity.slack.com/messages/connectors
Project-URL: Forums, https://forums.mysql.com/list.php?50
Project-URL: Blog, https://blogs.oracle.com/mysql/
Keywords: mysql,database,db,connector,driver
Classifier: Development Status :: 3 - Alpha
Classifier: Intended Audience :: Developers
Classifier: Topic :: Database
Classifier: Topic :: Software Development :: Libraries :: Python Modules
Classifier: License :: OSI Approved :: MIT License
Classifier: Programming Language :: Python :: 3
Classifier: Programming Language :: Python :: 3.7
Classifier: Programming Language :: Python :: 3.8
Classifier: Programming Language :: Python :: 3.9
Classifier: Programming Language :: Python :: 3.10
Classifier: Programming Language :: Python :: 3.11
Classifier: Operating System :: OS Independent
Requires-Python: >=3.7
License-File: LICENSE.txt
Requires-Dist: mysql-connector-python<9.0.0,>=8.0.0
Dynamic: author
Dynamic: author-email
Dynamic: classifier
Dynamic: description
Dynamic: description-content-type
Dynamic: home-page
Dynamic: keywords
Dynamic: license
Dynamic: license-file
Dynamic: project-url
Dynamic: requires-dist
Dynamic: requires-python
Dynamic: summary
